MANIFEST.in
README.md
setup.cfg
setup.py
Ctl/VERSION
Ctl/requirements-test.txt
Ctl/requirements.txt
django_namespace_perms/__init__.py
django_namespace_perms/admin.py
django_namespace_perms/apps.py
django_namespace_perms/constants.py
django_namespace_perms/exceptions.py
django_namespace_perms/models.py
django_namespace_perms/rest.py
django_namespace_perms/util.py
django_namespace_perms/views.py
django_namespace_perms.egg-info/PKG-INFO
django_namespace_perms.egg-info/SOURCES.txt
django_namespace_perms.egg-info/dependency_links.txt
django_namespace_perms.egg-info/top_level.txt
django_namespace_perms.egg-info/zip-safe
django_namespace_perms/auth/__init__.py
django_namespace_perms/auth/backends.py
django_namespace_perms/auth/models.py
django_namespace_perms/migrations/0001_initial.py
django_namespace_perms/migrations/__init__.py
django_namespace_perms/templatetags/__init__.py
django_namespace_perms/templatetags/nsp_tags.py
tests/__init__.py
tests/conftest.py
tests/test_nsp.py